apollo/__init__.py
apollo/main.py
apollo/commands/__init__.py
apollo/commands/build.py
apollo/commands/clean_up.py
apollo/commands/deploy.py
apollo/commands/gh_add.py
apollo/commands/gh_create.py
apollo/commands/gh_delete.py
apollo/commands/linear.py
apollo/utils/__init__.py
apollo/utils/config.py
apollo/utils/directories.py
apollo/utils/run_command.py
apollo_o1-1.1.3.dist-info/METADATA
apollo_o1-1.1.3.dist-info/WHEEL
apollo_o1-1.1.3.dist-info/entry_points.txt
apollo_o1-1.1.3.dist-info/top_level.txt
apollo_o1-1.1.3.dist-info/RECORD
