Metadata-Version: 2.2
Name: apollo-o1
Version: 1.1.3
Summary: An AI-powered Command-Line Interface designed to streamline the SDLC by automating project workflows, including source control, CI/CD, ticket and documentation generation, and other processes.
Home-page: https://github.com/dj-io/apollo
Author: Stratum Labs
Author-email: hq@stratumlabs.ai
Project-URL: Code, https://github.com/dj-io/apollo-o1
Project-URL: Documentation, https://github.com/dj-io/apollo-o1/blob/main/README.md
Classifier: Programming Language :: Python :: 3
Classifier: License :: OSI Approved :: MIT License
Classifier: Operating System :: OS Independent
Classifier: Intended Audience :: Developers
Classifier: Topic :: Software Development :: Build Tools
Classifier: Topic :: Utilities
Requires-Python: >=3.7
Requires-Dist: questionary
Requires-Dist: click
Requires-Dist: python-dotenv
Requires-Dist: halo
Requires-Dist: flake8
Requires-Dist: black
Provides-Extra: dev
Requires-Dist: pytest; extra == "dev"
Dynamic: author
Dynamic: author-email
Dynamic: classifier
Dynamic: description
Dynamic: description-content-type
Dynamic: home-page
Dynamic: project-url
Dynamic: provides-extra
Dynamic: requires-dist
Dynamic: requires-python
Dynamic: summary
